flutter/__init__.py
flutter/py.typed
flutter-0.1.dist-info/LICENSE.ISC
flutter-0.1.dist-info/WHEEL
flutter-0.1.dist-info/METADATA
flutter-0.1.dist-info/RECORD
